txlog/__init__.py
txlog/txlog.py
txlog/utils.py
txlog-2.2308.0.dist-info/LICENSE
txlog-2.2308.0.dist-info/METADATA
txlog-2.2308.0.dist-info/WHEEL
txlog-2.2308.0.dist-info/top_level.txt
txlog-2.2308.0.dist-info/RECORD
