Metadata-Version: 2.1
Name: txlog
Version: 2.2308.0
Summary: Crash-resistant Python code made easy
Home-page: https://github.com/labteral/txlog
Author: Rodrigo Martínez
Author-email: dev@brunneis.com
License: GNU General Public License v3.0
Classifier: Development Status :: 4 - Beta
Classifier: Environment :: Console
Classifier: Intended Audience :: Developers
Classifier: License :: OSI Approved :: GNU General Public License v3 (GPLv3)
Classifier: Operating System :: POSIX :: Linux
Classifier: Programming Language :: Python :: 3.6
Classifier: Programming Language :: Python :: Implementation :: PyPy
Classifier: Topic :: Software Development :: Libraries :: Python Modules
License-File: LICENSE
Requires-Dist: easyrocks
